sphinx_sqlalchemy/__init__.py
sphinx_sqlalchemy/main.py
sphinx_sqlalchemy-0.3.0.dist-info/LICENSE
sphinx_sqlalchemy-0.3.0.dist-info/WHEEL
sphinx_sqlalchemy-0.3.0.dist-info/METADATA
sphinx_sqlalchemy-0.3.0.dist-info/RECORD
